.hgignore
.hgtags
README.txt
bootstrap.py
buildout.cfg
setup.py
docs/HISTORY.txt
nilo/__init__.py
nilo.webgallery.egg-info/PKG-INFO
nilo.webgallery.egg-info/SOURCES.txt
nilo.webgallery.egg-info/dependency_links.txt
nilo.webgallery.egg-info/entry_points.txt
nilo.webgallery.egg-info/namespace_packages.txt
nilo.webgallery.egg-info/not-zip-safe
nilo.webgallery.egg-info/requires.txt
nilo.webgallery.egg-info/top_level.txt
nilo/webgallery/__init__.py
nilo/webgallery/handler.py
nilo/webgallery/publisher.py
nilo/webgallery/runscript.py
nilo/webgallery/server.py
nilo/webgallery/template.py
nilo/webgallery/thumbnailer.py
nilo/webgallery/resources/jquery-latest.pack.js
nilo/webgallery/resources/loadingAnimation.gif
nilo/webgallery/resources/macFFBgHack.png
nilo/webgallery/resources/style.css
nilo/webgallery/resources/thickbox-compressed.js
nilo/webgallery/templates/default.html